{
  "index": 52,
  "id": "5e05c966465a4b00068d616e",
  "name": {
    "en": "Bamboo",
    "zh-Hans": "竹林",
    "zh-Hant": "竹林",
    "ja": "竹林",
    "es": "Bambú",
    "ko": "대나무",
    "ru": "Бамбук"
  },
  "sub_title": {
    "en": "Sitting in the rustling bamboo forest",
    "zh-Hans": "独坐幽篁里",
    "zh-Hant": "獨坐幽篁裡",
    "ja": "ざわめいた竹林に一人で座る",
    "es": "Sentando en un bosque de bambú surusante ",
    "ko": "살랑살랑하는 바람이 불고 있는 대나무 숲에서 앉아 있다",
    "ru": "Сидя в шелестящем бамбуковом лесу"
  },
  "image_url": "https://pics.tide.moreless.io/scenes/lqW9dkPrcreUG3Yi1I7Z4_-_PNsm/shots",
  "sound_url": "https://pics.tide.moreless.io/demo_sounds/Fo7U7R_yu1yzX49_EBeaWjgUUGjR",
  "low_quality_sound_url": "https://pics.tide.moreless.io/demo_sounds/low_quality_Fo7U7R_yu1yzX49_EBeaWjgUUGjR",
  "resource": {
    "guid": "5e05c966465a4b00068d616e",
    "name": "声音场景 - 竹林 - 音频资源",
    "demo_sound_url": "https://pics.tide.moreless.io/demo_sounds/Fo7U7R_yu1yzX49_EBeaWjgUUGjR",
    "demo_low_quality_url": "https://pics.tide.moreless.io/demo_sounds/low_quality_Fo7U7R_yu1yzX49_EBeaWjgUUGjR",
    "demo_multichannel_url": "",
    "demo_dolby_url": "",
    "hash": "lnLiH1oXjBjt3oX9SqrAxAE_m8l6",
    "hash_key": "sounds/lnLiH1oXjBjt3oX9SqrAxAE_m8l6",
    "low_quality_hash": "low_quality_lnLiH1oXjBjt3oX9SqrAxAE_m8l6",
    "low_quality_hash_key": "sounds/low_quality_lnLiH1oXjBjt3oX9SqrAxAE_m8l6",
    "multichannel_hash": "",
    "multichannel_hash_key": "",
    "dolby_hash": "",
    "dolby_hash_key": "",
    "loop_hash": "",
    "loop_hash_key": "",
    "human_voice_hash": "",
    "human_voice_hash_key": "",
    "max_volume_per": 70,
    "duration": 0,
    "size_in_bytes": 11901870,
    "status": "published",
    "has_white_noise": true,
    "has_human_voice": false,
    "is_default_duration": false,
    "tail_scene_id": "",
    "tail_scene_vol_pct": 0,
    "tail_recommend_scene_ids": [],
    "tail_has_mute_option": false,
    "updated_at": 16544989231592048,
    "created_at": 0
  }
}