{
  "index": 98,
  "id": "5af723f5afae2f000530f6be",
  "name": {
    "en": "Pond",
    "zh-Hans": "池塘",
    "zh-Hant": "池塘",
    "ja": "池",
    "es": "Estanque",
    "ko": "못",
    "ru": "Пруд"
  },
  "sub_title": {
    "en": "An old pond",
    "zh-Hans": "闲寂的古池旁",
    "zh-Hant": "閒寂的古池旁",
    "ja": "古池や",
    "es": "Un viejo estanque",
    "ko": "오래된 못",
    "ru": "Старый пруд"
  },
  "image_url": "https://pics.tide.moreless.io/scenes/lum8QlnD-qOWuMUYxfVih69xcfcv/shots",
  "sound_url": "https://pics.tide.moreless.io/demo_sounds/FihawfkUOBhXDbqKGVbdkfwFFWS2",
  "low_quality_sound_url": "https://pics.tide.moreless.io/demo_sounds/low_quality_FihawfkUOBhXDbqKGVbdkfwFFWS2",
  "resource": {
    "guid": "5af723f5afae2f000530f6be",
    "name": "声音场景 - 池塘 - 音频资源",
    "demo_sound_url": "https://pics.tide.moreless.io/demo_sounds/FihawfkUOBhXDbqKGVbdkfwFFWS2",
    "demo_low_quality_url": "https://pics.tide.moreless.io/demo_sounds/low_quality_FihawfkUOBhXDbqKGVbdkfwFFWS2",
    "demo_multichannel_url": "",
    "demo_dolby_url": "",
    "hash": "lpyOoX7cWGdmS2srIg2b_KBNLBja",
    "hash_key": "sounds/lpyOoX7cWGdmS2srIg2b_KBNLBja",
    "low_quality_hash": "low_quality_lpyOoX7cWGdmS2srIg2b_KBNLBja",
    "low_quality_hash_key": "sounds/low_quality_lpyOoX7cWGdmS2srIg2b_KBNLBja",
    "multichannel_hash": "",
    "multichannel_hash_key": "",
    "dolby_hash": "",
    "dolby_hash_key": "",
    "loop_hash": "",
    "loop_hash_key": "",
    "human_voice_hash": "",
    "human_voice_hash_key": "",
    "max_volume_per": 70,
    "duration": 0,
    "size_in_bytes": 6476792,
    "status": "published",
    "has_white_noise": true,
    "has_human_voice": false,
    "is_default_duration": false,
    "tail_scene_id": "",
    "tail_scene_vol_pct": 0,
    "tail_recommend_scene_ids": null,
    "tail_has_mute_option": false,
    "updated_at": 16544980648269588,
    "created_at": 0
  }
}