{
  "index": 158,
  "id": "5a560c333ea0bf00086a36a6",
  "name": {
    "en": "Library",
    "zh-Hans": "图书馆",
    "zh-Hant": "圖書館",
    "ja": "図書館",
    "es": "Biblioteca",
    "ko": "도서관",
    "ru": "Библиотека"
  },
  "sub_title": {
    "en": "Back to school",
    "zh-Hans": "重返学校时光",
    "zh-Hant": "重返學校時光",
    "ja": "再び学校生活に戻る",
    "es": "Regresar al tiempo de la escuela",
    "ko": "학생 시절로 다시 돌아갑니다",
    "ru": "Обратно в школу"
  },
  "image_url": "https://pics.tide.moreless.io/scenes/llQqbQwj2K7x4B26a4J6zStiUbwT/shots",
  "sound_url": "https://pics.tide.moreless.io/demo_sounds/Fs-UQ7glUwaLj_xqJuHCc07kersj",
  "low_quality_sound_url": "https://pics.tide.moreless.io/demo_sounds/low_quality_Fs-UQ7glUwaLj_xqJuHCc07kersj",
  "resource": {
    "guid": "5a560c333ea0bf00086a36a6",
    "name": "声音场景 - 图书馆 - 音频资源",
    "demo_sound_url": "https://pics.tide.moreless.io/demo_sounds/Fs-UQ7glUwaLj_xqJuHCc07kersj",
    "demo_low_quality_url": "https://pics.tide.moreless.io/demo_sounds/low_quality_Fs-UQ7glUwaLj_xqJuHCc07kersj",
    "demo_multichannel_url": "",
    "demo_dolby_url": "",
    "hash": "lt4TJpfSDjai1MvC80-KHuqotVtr",
    "hash_key": "sounds/lt4TJpfSDjai1MvC80-KHuqotVtr",
    "low_quality_hash": "low_quality_lt4TJpfSDjai1MvC80-KHuqotVtr",
    "low_quality_hash_key": "sounds/low_quality_lt4TJpfSDjai1MvC80-KHuqotVtr",
    "multichannel_hash": "",
    "multichannel_hash_key": "",
    "dolby_hash": "",
    "dolby_hash_key": "",
    "loop_hash": "",
    "loop_hash_key": "",
    "human_voice_hash": "",
    "human_voice_hash_key": "",
    "max_volume_per": 70,
    "duration": 0,
    "size_in_bytes": 9505312,
    "status": "published",
    "has_white_noise": true,
    "has_human_voice": false,
    "is_default_duration": false,
    "tail_scene_id": "",
    "tail_scene_vol_pct": 0,
    "tail_recommend_scene_ids": [],
    "tail_has_mute_option": false,
    "updated_at": 16544965878284910,
    "created_at": 0
  }
}